petstore_trilogy/__init__.py
petstore_trilogy/api_client.py
petstore_trilogy/api_response.py
petstore_trilogy/configuration.py
petstore_trilogy/exceptions.py
petstore_trilogy/py.typed
petstore_trilogy/rest.py
petstore_trilogy/api/__init__.py
petstore_trilogy/api/pet_api.py
petstore_trilogy/api/store_api.py
petstore_trilogy/api/user_api.py
petstore_trilogy/models/__init__.py
petstore_trilogy/models/address.py
petstore_trilogy/models/api_response.py
petstore_trilogy/models/category.py
petstore_trilogy/models/customer.py
petstore_trilogy/models/order.py
petstore_trilogy/models/pet.py
petstore_trilogy/models/tag.py
petstore_trilogy/models/user.py
petstore_trilogy-1.0.0.dist-info/METADATA
petstore_trilogy-1.0.0.dist-info/WHEEL
petstore_trilogy-1.0.0.dist-info/top_level.txt
petstore_trilogy-1.0.0.dist-info/RECORD
